<annotation verified="no">
  <folder>Elmer broodjes</folder>
  <filename>Broodjes (65)</filename>
  <path>C:\Users\Elmer\OneDrive for Business\Dero - Broodjes\Dero - Deep Learning\dataset\dataset brood 300x300\Elmer broodjes\Broodjes (65).jpg</path>
  <source>
    <database>Unknown</database>
  </source>
  <size>
    <width>300</width>
    <height>300</height>
    <depth>3</depth>
  </size>
  <segmented>0</segmented>
  <object>
    <type>robndbox</type>
    <name>broodjes onderkant</name>
    <pose>Unspecified</pose>
    <truncated>0</truncated>
    <difficult>0</difficult>
    <robndbox>
      <cx>191.628</cx>
      <cy>166.0</cy>
      <w>85.3014</w>
      <h>24.5697</h>
      <angle>3.131593</angle>
    </robndbox>
  </object>
  <object>
    <type>robndbox</type>
    <name>broodjes onderkant</name>
    <pose>Unspecified</pose>
    <truncated>0</truncated>
    <difficult>0</difficult>
    <robndbox>
      <cx>181.128</cx>
      <cy>118.5</cy>
      <w>70.8596</w>
      <h>32.2012</h>
      <angle>0.79</angle>
    </robndbox>
  </object>
  <object>
    <type>robndbox</type>
    <name>broodjes onderkant</name>
    <pose>Unspecified</pose>
    <truncated>0</truncated>
    <difficult>0</difficult>
    <robndbox>
      <cx>66.4745</cx>
      <cy>200.348</cy>
      <w>73.9795</w>
      <h>32.3448</h>
      <angle>1.8</angle>
    </robndbox>
  </object>
  <object>
    <type>robndbox</type>
    <name>broodjes bovenkant</name>
    <pose>Unspecified</pose>
    <truncated>0</truncated>
    <difficult>0</difficult>
    <robndbox>
      <cx>97.7254</cx>
      <cy>77.5557</cy>
      <w>85.5845</w>
      <h>28.3311</h>
      <angle>0.52</angle>
    </robndbox>
  </object>
  <object>
    <type>robndbox</type>
    <name>broodjes bovenkant</name>
    <pose>Unspecified</pose>
    <truncated>0</truncated>
    <difficult>0</difficult>
    <robndbox>
      <cx>233.2909</cx>
      <cy>100.9628</cy>
      <w>66.483</w>
      <h>33.0082</h>
      <angle>1.2</angle>
    </robndbox>
  </object>
  <object>
    <type>robndbox</type>
    <name>broodjes bovenkant</name>
    <pose>Unspecified</pose>
    <truncated>0</truncated>
    <difficult>0</difficult>
    <robndbox>
      <cx>42.7177</cx>
      <cy>119.6759</cy>
      <w>77.8974</w>
      <h>31.9808</h>
      <angle>0.84</angle>
    </robndbox>
  </object>
  <object>
    <type>robndbox</type>
    <name>broodjes bovenkant</name>
    <pose>Unspecified</pose>
    <truncated>0</truncated>
    <difficult>0</difficult>
    <robndbox>
      <cx>145.7322</cx>
      <cy>221.2434</cy>
      <w>78.2917</w>
      <h>28.4221</h>
      <angle>2.271593</angle>
    </robndbox>
  </object>
  <object>
    <type>robndbox</type>
    <name>broodjes bovenkant</name>
    <pose>Unspecified</pose>
    <truncated>0</truncated>
    <difficult>0</difficult>
    <robndbox>
      <cx>215.0734</cx>
      <cy>216.1728</cy>
      <w>68.7951</w>
      <h>33.6784</h>
      <angle>2.131593</angle>
    </robndbox>
  </object>
  <object>
    <type>robndbox</type>
    <name>broodjes bovenkant</name>
    <pose>Unspecified</pose>
    <truncated>0</truncated>
    <difficult>0</difficult>
    <robndbox>
      <cx>111.8835</cx>
      <cy>148.0594</cy>
      <w>68.3519</w>
      <h>33.5177</h>
      <angle>1.931593</angle>
    </robndbox>
  </object>
</annotation>
