<annotation verified="no">
  <folder>Elmer broodjes</folder>
  <filename>Broodjes (87)</filename>
  <path>C:\Users\Elmer\OneDrive for Business\Dero - Broodjes\Dero - Deep Learning\dataset\dataset brood 300x300\Elmer broodjes\Broodjes (87).jpg</path>
  <source>
    <database>Unknown</database>
  </source>
  <size>
    <width>300</width>
    <height>300</height>
    <depth>3</depth>
  </size>
  <segmented>0</segmented>
  <object>
    <type>robndbox</type>
    <name>broodjes bovenkant</name>
    <pose>Unspecified</pose>
    <truncated>0</truncated>
    <difficult>0</difficult>
    <robndbox>
      <cx>116.2896</cx>
      <cy>83.4454</cy>
      <w>62.6095</w>
      <h>30.2387</h>
      <angle>2.681593</angle>
    </robndbox>
  </object>
  <object>
    <type>robndbox</type>
    <name>broodjes bovenkant</name>
    <pose>Unspecified</pose>
    <truncated>0</truncated>
    <difficult>0</difficult>
    <robndbox>
      <cx>196.628</cx>
      <cy>85.0</cy>
      <w>60.9992</w>
      <h>30.3166</h>
      <angle>0.52</angle>
    </robndbox>
  </object>
  <object>
    <type>robndbox</type>
    <name>broodjes bovenkant</name>
    <pose>Unspecified</pose>
    <truncated>0</truncated>
    <difficult>0</difficult>
    <robndbox>
      <cx>45.8229</cx>
      <cy>169.4856</cy>
      <w>75.1658</w>
      <h>28.3642</h>
      <angle>1.641593</angle>
    </robndbox>
  </object>
  <object>
    <type>robndbox</type>
    <name>broodjes bovenkant</name>
    <pose>Unspecified</pose>
    <truncated>0</truncated>
    <difficult>0</difficult>
    <robndbox>
      <cx>237.0425</cx>
      <cy>159.702</cy>
      <w>82.0365</w>
      <h>22.3246</h>
      <angle>1.731593</angle>
    </robndbox>
  </object>
  <object>
    <type>robndbox</type>
    <name>broodjes onderkant</name>
    <pose>Unspecified</pose>
    <truncated>0</truncated>
    <difficult>0</difficult>
    <robndbox>
      <cx>200.0666</cx>
      <cy>211.3786</cy>
      <w>66.2133</w>
      <h>29.3716</h>
      <angle>0.33</angle>
    </robndbox>
  </object>
  <object>
    <type>robndbox</type>
    <name>broodjes onderkant</name>
    <pose>Unspecified</pose>
    <truncated>0</truncated>
    <difficult>0</difficult>
    <robndbox>
      <cx>178.4474</cx>
      <cy>133.7257</cy>
      <w>74.9543</w>
      <h>23.7694</h>
      <angle>1.31</angle>
    </robndbox>
  </object>
  <object>
    <type>robndbox</type>
    <name>broodjes onderkant</name>
    <pose>Unspecified</pose>
    <truncated>0</truncated>
    <difficult>0</difficult>
    <robndbox>
      <cx>135.718</cx>
      <cy>155.3074</cy>
      <w>72.8972</w>
      <h>25.6798</h>
      <angle>1.1</angle>
    </robndbox>
  </object>
  <object>
    <type>robndbox</type>
    <name>broodjes onderkant</name>
    <pose>Unspecified</pose>
    <truncated>0</truncated>
    <difficult>0</difficult>
    <robndbox>
      <cx>99.9537</cx>
      <cy>172.8922</cy>
      <w>70.1706</w>
      <h>29.5214</h>
      <angle>0.7</angle>
    </robndbox>
  </object>
  <object>
    <type>robndbox</type>
    <name>broodjes onderkant</name>
    <pose>Unspecified</pose>
    <truncated>0</truncated>
    <difficult>0</difficult>
    <robndbox>
      <cx>93.1859</cx>
      <cy>232.6323</cy>
      <w>72.4703</w>
      <h>27.3229</h>
      <angle>0.88</angle>
    </robndbox>
  </object>
  <object>
    <type>robndbox</type>
    <name>broodjes onderkant</name>
    <pose>Unspecified</pose>
    <truncated>0</truncated>
    <difficult>0</difficult>
    <robndbox>
      <cx>159.9822</cx>
      <cy>248.72</cy>
      <w>75.2456</w>
      <h>25.2939</h>
      <angle>0.93</angle>
    </robndbox>
  </object>
</annotation>
