<annotation verified="no">
  <folder>New shit</folder>
  <filename>Broodjes (127)</filename>
  <path>C:\Users\Jaime\Downloads\dataset 300x300\afbeelding brood\New shit\Broodjes (127).jpg</path>
  <source>
    <database>Unknown</database>
  </source>
  <size>
    <width>300</width>
    <height>300</height>
    <depth>3</depth>
  </size>
  <segmented>0</segmented>
  <object>
    <type>robndbox</type>
    <name>broodjes bovenkant</name>
    <pose>Unspecified</pose>
    <truncated>0</truncated>
    <difficult>0</difficult>
    <robndbox>
      <cx>252.5183</cx>
      <cy>205.1122</cy>
      <w>74.9995</w>
      <h>31.2953</h>
      <angle>2.494778</angle>
    </robndbox>
  </object>
  <object>
    <type>robndbox</type>
    <name>broodjes bovenkant</name>
    <pose>Unspecified</pose>
    <truncated>0</truncated>
    <difficult>0</difficult>
    <robndbox>
      <cx>71.5183</cx>
      <cy>244.1122</cy>
      <w>74.9995</w>
      <h>31.2953</h>
      <angle>2.494778</angle>
    </robndbox>
  </object>
  <object>
    <type>robndbox</type>
    <name>broodjes bovenkant</name>
    <pose>Unspecified</pose>
    <truncated>0</truncated>
    <difficult>0</difficult>
    <robndbox>
      <cx>64.6124</cx>
      <cy>175.9478</cy>
      <w>69.6082</w>
      <h>33.4905</h>
      <angle>0.443185</angle>
    </robndbox>
  </object>
  <object>
    <type>robndbox</type>
    <name>broodjes bovenkant</name>
    <pose>Unspecified</pose>
    <truncated>0</truncated>
    <difficult>0</difficult>
    <robndbox>
      <cx>68.6729</cx>
      <cy>101.7339</cy>
      <w>66.4845</w>
      <h>36.2763</h>
      <angle>0.343185</angle>
    </robndbox>
  </object>
  <object>
    <type>robndbox</type>
    <name>broodjes bovenkant</name>
    <pose>Unspecified</pose>
    <truncated>0</truncated>
    <difficult>0</difficult>
    <robndbox>
      <cx>135.472</cx>
      <cy>96.7346</cy>
      <w>78.305</w>
      <h>28.7612</h>
      <angle>1.033185</angle>
    </robndbox>
  </object>
  <object>
    <type>robndbox</type>
    <name>broodjes bovenkant</name>
    <pose>Unspecified</pose>
    <truncated>0</truncated>
    <difficult>0</difficult>
    <robndbox>
      <cx>184.8184</cx>
      <cy>101.504</cy>
      <w>85.977</w>
      <h>25.7765</h>
      <angle>1.613185</angle>
    </robndbox>
  </object>
  <object>
    <type>robndbox</type>
    <name>broodjes bovenkant</name>
    <pose>Unspecified</pose>
    <truncated>0</truncated>
    <difficult>0</difficult>
    <robndbox>
      <cx>232.2394</cx>
      <cy>98.9974</cy>
      <w>78.0902</w>
      <h>30.2905</h>
      <angle>0.923185</angle>
    </robndbox>
  </object>
  <object>
    <type>robndbox</type>
    <name>broodjes onderkant</name>
    <pose>Unspecified</pose>
    <truncated>0</truncated>
    <difficult>0</difficult>
    <robndbox>
      <cx>214.3709</cx>
      <cy>166.5486</cy>
      <w>72.6903</w>
      <h>32.1295</h>
      <angle>3.124778</angle>
    </robndbox>
  </object>
  <object>
    <type>robndbox</type>
    <name>broodjes onderkant</name>
    <pose>Unspecified</pose>
    <truncated>0</truncated>
    <difficult>0</difficult>
    <robndbox>
      <cx>131.4429</cx>
      <cy>161.8802</cy>
      <w>79.0388</w>
      <h>29.1817</h>
      <angle>0.824778</angle>
    </robndbox>
  </object>
  <object>
    <type>robndbox</type>
    <name>broodjes onderkant</name>
    <pose>Unspecified</pose>
    <truncated>0</truncated>
    <difficult>0</difficult>
    <robndbox>
      <cx>189.8989</cx>
      <cy>225.6892</cy>
      <w>92.6275</w>
      <h>25.9636</h>
      <angle>1.194778</angle>
    </robndbox>
  </object>
  <object>
    <type>robndbox</type>
    <name>broodjes onderkant</name>
    <pose>Unspecified</pose>
    <truncated>0</truncated>
    <difficult>0</difficult>
    <robndbox>
      <cx>141.3525</cx>
      <cy>235.7708</cy>
      <w>80.692</w>
      <h>29.7923</h>
      <angle>0.794778</angle>
    </robndbox>
  </object>
</annotation>
