<annotation verified="no">
  <folder>New shit</folder>
  <filename>Broodjes (188)</filename>
  <path>C:\Users\Jaime\Downloads\dataset 300x300\afbeelding brood\New shit\Broodjes (188).jpg</path>
  <source>
    <database>Unknown</database>
  </source>
  <size>
    <width>300</width>
    <height>300</height>
    <depth>3</depth>
  </size>
  <segmented>0</segmented>
  <object>
    <type>robndbox</type>
    <name>broodjes bovenkant</name>
    <pose>Unspecified</pose>
    <truncated>0</truncated>
    <difficult>0</difficult>
    <robndbox>
      <cx>178.5638</cx>
      <cy>92.1121</cy>
      <w>87.091</w>
      <h>24.9924</h>
      <angle>1.311593</angle>
    </robndbox>
  </object>
  <object>
    <type>robndbox</type>
    <name>broodjes bovenkant</name>
    <pose>Unspecified</pose>
    <truncated>0</truncated>
    <difficult>0</difficult>
    <robndbox>
      <cx>125.0638</cx>
      <cy>105.6121</cy>
      <w>80.0685</w>
      <h>25.82</h>
      <angle>1.311593</angle>
    </robndbox>
  </object>
  <object>
    <type>robndbox</type>
    <name>broodjes onderkant</name>
    <pose>Unspecified</pose>
    <truncated>0</truncated>
    <difficult>0</difficult>
    <robndbox>
      <cx>165.8406</cx>
      <cy>157.3215</cy>
      <w>88.0557</w>
      <h>22.4616</h>
      <angle>1.311593</angle>
    </robndbox>
  </object>
  <object>
    <type>robndbox</type>
    <name>broodjes onderkant</name>
    <pose>Unspecified</pose>
    <truncated>0</truncated>
    <difficult>0</difficult>
    <robndbox>
      <cx>90.3692</cx>
      <cy>84.1074</cy>
      <w>82.5797</w>
      <h>27.5326</h>
      <angle>2.063186</angle>
    </robndbox>
  </object>
  <object>
    <type>robndbox</type>
    <name>broodjes onderkant</name>
    <pose>Unspecified</pose>
    <truncated>0</truncated>
    <difficult>0</difficult>
    <robndbox>
      <cx>190.7186</cx>
      <cy>35.3652</cy>
      <w>70.3819</w>
      <h>34.4985</h>
      <angle>0.191593</angle>
    </robndbox>
  </object>
  <object>
    <type>robndbox</type>
    <name>broodjes onderkant</name>
    <pose>Unspecified</pose>
    <truncated>0</truncated>
    <difficult>0</difficult>
    <robndbox>
      <cx>266.7041</cx>
      <cy>101.0704</cy>
      <w>80.6733</w>
      <h>28.7847</h>
      <angle>1.443186</angle>
    </robndbox>
  </object>
  <object>
    <type>robndbox</type>
    <name>broodjes onderkant</name>
    <pose>Unspecified</pose>
    <truncated>0</truncated>
    <difficult>0</difficult>
    <robndbox>
      <cx>255.1342</cx>
      <cy>181.9168</cy>
      <w>77.8182</w>
      <h>32.6812</h>
      <angle>2.043186</angle>
    </robndbox>
  </object>
  <object>
    <type>robndbox</type>
    <name>broodjes onderkant</name>
    <pose>Unspecified</pose>
    <truncated>0</truncated>
    <difficult>0</difficult>
    <robndbox>
      <cx>169.8233</cx>
      <cy>223.7212</cy>
      <w>65.0721</w>
      <h>34.9763</h>
      <angle>3.104778</angle>
    </robndbox>
  </object>
  <object>
    <type>robndbox</type>
    <name>broodjes onderkant</name>
    <pose>Unspecified</pose>
    <truncated>0</truncated>
    <difficult>0</difficult>
    <robndbox>
      <cx>207.9487</cx>
      <cy>241.2365</cy>
      <w>69.8863</w>
      <h>35.2315</h>
      <angle>2.514778</angle>
    </robndbox>
  </object>
  <object>
    <type>robndbox</type>
    <name>broodjes onderkant</name>
    <pose>Unspecified</pose>
    <truncated>0</truncated>
    <difficult>0</difficult>
    <robndbox>
      <cx>74.228</cx>
      <cy>233.972</cy>
      <w>79.3236</w>
      <h>33.0382</h>
      <angle>0.874778</angle>
    </robndbox>
  </object>
  <object>
    <type>robndbox</type>
    <name>broodjes onderkant</name>
    <pose>Unspecified</pose>
    <truncated>0</truncated>
    <difficult>0</difficult>
    <robndbox>
      <cx>141.263</cx>
      <cy>270.3582</cy>
      <w>68.0952</w>
      <h>37.5157</h>
      <angle>0.324778</angle>
    </robndbox>
  </object>
</annotation>
