<annotation verified="no">
  <folder>New shit</folder>
  <filename>Broodjes (207)</filename>
  <path>C:\Users\Jaime\Downloads\dataset 300x300\afbeelding brood\New shit\Broodjes (207).jpg</path>
  <source>
    <database>Unknown</database>
  </source>
  <size>
    <width>300</width>
    <height>300</height>
    <depth>3</depth>
  </size>
  <segmented>0</segmented>
  <object>
    <type>robndbox</type>
    <name>broodjes bovenkant</name>
    <pose>Unspecified</pose>
    <truncated>0</truncated>
    <difficult>0</difficult>
    <robndbox>
      <cx>103.3855</cx>
      <cy>82.4518</cy>
      <w>32.4872</w>
      <h>68.3033</h>
      <angle>0.983185</angle>
    </robndbox>
  </object>
  <object>
    <type>robndbox</type>
    <name>broodjes bovenkant</name>
    <pose>Unspecified</pose>
    <truncated>0</truncated>
    <difficult>0</difficult>
    <robndbox>
      <cx>162.3855</cx>
      <cy>156.4518</cy>
      <w>32.4872</w>
      <h>68.3033</h>
      <angle>1.453185</angle>
    </robndbox>
  </object>
  <object>
    <type>robndbox</type>
    <name>broodjes bovenkant</name>
    <pose>Unspecified</pose>
    <truncated>0</truncated>
    <difficult>0</difficult>
    <robndbox>
      <cx>158.5526</cx>
      <cy>210.2333</cy>
      <w>36.1105</w>
      <h>62.4987</h>
      <angle>1.803185</angle>
    </robndbox>
  </object>
  <object>
    <type>robndbox</type>
    <name>broodjes bovenkant</name>
    <pose>Unspecified</pose>
    <truncated>0</truncated>
    <difficult>0</difficult>
    <robndbox>
      <cx>143.4364</cx>
      <cy>243.5532</cy>
      <w>38.4317</w>
      <h>66.9016</h>
      <angle>2.153185</angle>
    </robndbox>
  </object>
  <object>
    <type>robndbox</type>
    <name>broodjes bovenkant</name>
    <pose>Unspecified</pose>
    <truncated>0</truncated>
    <difficult>0</difficult>
    <robndbox>
      <cx>220.1768</cx>
      <cy>164.781</cy>
      <w>30.5465</w>
      <h>84.7696</h>
      <angle>0.153185</angle>
    </robndbox>
  </object>
  <object>
    <type>robndbox</type>
    <name>broodjes onderkant</name>
    <pose>Unspecified</pose>
    <truncated>0</truncated>
    <difficult>0</difficult>
    <robndbox>
      <cx>132.3855</cx>
      <cy>123.4518</cy>
      <w>32.4872</w>
      <h>68.3033</h>
      <angle>1.133185</angle>
    </robndbox>
  </object>
  <object>
    <type>robndbox</type>
    <name>broodjes onderkant</name>
    <pose>Unspecified</pose>
    <truncated>0</truncated>
    <difficult>0</difficult>
    <robndbox>
      <cx>85.8389</cx>
      <cy>184.7357</cy>
      <w>30.2984</w>
      <h>86.7639</h>
      <angle>2.974778</angle>
    </robndbox>
  </object>
  <object>
    <type>robndbox</type>
    <name>broodjes onderkant</name>
    <pose>Unspecified</pose>
    <truncated>0</truncated>
    <difficult>0</difficult>
    <robndbox>
      <cx>182.2282</cx>
      <cy>90.0758</cy>
      <w>31.1812</w>
      <h>73.9757</h>
      <angle>2.013185</angle>
    </robndbox>
  </object>
  <object>
    <type>robndbox</type>
    <name>broodjes onderkant</name>
    <pose>Unspecified</pose>
    <truncated>0</truncated>
    <difficult>0</difficult>
    <robndbox>
      <cx>238.6624</cx>
      <cy>77.408</cy>
      <w>30.0329</w>
      <h>90.846</h>
      <angle>2.903185</angle>
    </robndbox>
  </object>
  <object>
    <type>robndbox</type>
    <name>broodjes onderkant</name>
    <pose>Unspecified</pose>
    <truncated>0</truncated>
    <difficult>0</difficult>
    <robndbox>
      <cx>277.048</cx>
      <cy>146.51</cy>
      <w>29.7074</w>
      <h>85.0129</h>
      <angle>0.181592</angle>
    </robndbox>
  </object>
  <object>
    <type>robndbox</type>
    <name>broodjes onderkant</name>
    <pose>Unspecified</pose>
    <truncated>0</truncated>
    <difficult>0</difficult>
    <robndbox>
      <cx>232.0108</cx>
      <cy>231.5005</cy>
      <w>32.0423</w>
      <h>79.1286</h>
      <angle>0.711592</angle>
    </robndbox>
  </object>
</annotation>
